baikalctl/__init__.py
baikalctl/cli.py
baikalctl/client.py
baikalctl/exception_handler.py
baikalctl/firefox_profile.py
baikalctl/server.py
baikalctl/shell.py
baikalctl/version.py
baikalctl-1.2.0.dist-info/entry_points.txt
baikalctl-1.2.0.dist-info/LICENSE
baikalctl-1.2.0.dist-info/WHEEL
baikalctl-1.2.0.dist-info/METADATA
baikalctl-1.2.0.dist-info/RECORD
